python_liftbridge/__init__.py
python_liftbridge/api_pb2.py
python_liftbridge/api_pb2_grpc.py
python_liftbridge/base.py
python_liftbridge/errors.py
python_liftbridge/message.py
python_liftbridge/python_liftbridge.py
python_liftbridge/stream.py
python_liftbridge/version.py
python_liftbridge-0.0.7.dist-info/LICENSE.md
python_liftbridge-0.0.7.dist-info/METADATA
python_liftbridge-0.0.7.dist-info/WHEEL
python_liftbridge-0.0.7.dist-info/top_level.txt
python_liftbridge-0.0.7.dist-info/RECORD
