Metadata-Version: 2.1
Name: python-liftbridge
Version: 0.0.7
Summary: Python client for Liftbridge.
Home-page: https://github.com/dgzlopes/python-liftbridge
Author: Daniel González Lopes
Author-email: danielgonzalezlopes@gmail.com
License: Apache Software License (Apache License, Version 2.0)
Platform: UNKNOWN
Classifier: Development Status :: 3 - Alpha
Classifier: Intended Audience :: Developers
Classifier: Natural Language :: English
Classifier: Programming Language :: Python :: 3.6
Classifier: Programming Language :: Python :: 3.7
Classifier: License :: OSI Approved :: Apache Software License
Classifier: Topic :: Software Development :: Libraries :: Python Modules
Classifier: Topic :: System :: Systems Administration
Classifier: Topic :: System :: Networking
Requires-Dist: grpcio (<2,>=1.23.0)
